stylometry/__init__.py
stylometry/ai_interface.py
stylometry/boilerplate.py
stylometry/cli.py
stylometry/delta.py
stylometry/loaders.py
stylometry/metrics.py
stylometry/models.py
stylometry/normalizer.py
stylometry/reporting.py
stylometry/semantic.py
stylometry/utils.py
stylometry_cli-1.0.0.dist-info/licenses/LICENSE
stylometry_cli-1.0.0.dist-info/METADATA
stylometry_cli-1.0.0.dist-info/WHEEL
stylometry_cli-1.0.0.dist-info/entry_points.txt
stylometry_cli-1.0.0.dist-info/top_level.txt
stylometry_cli-1.0.0.dist-info/RECORD
