Metadata-Version: 2.4
Name: stylometry-cli
Version: 1.0.0
Summary: Quantitative author fingerprinting & stylometric analysis - offline CLI tool
Author: SpectreDeath
License: MIT
Project-URL: Homepage, https://github.com/SpectreDeath/stylometry-cli
Project-URL: Documentation, https://github.com/SpectreDeath/stylometry-cli#readme
Project-URL: Repository, https://github.com/SpectreDeath/stylometry-cli.git
Project-URL: Issues, https://github.com/SpectreDeath/stylometry-cli/issues
Keywords: stylometry,authorship,nlp,linguistics,forensics,text-analysis
Classifier: Development Status :: 4 - Beta
Classifier: Environment :: Console
Classifier: Intended Audience :: Developers
Classifier: Intended Audience :: Science/Research
Classifier: License :: OSI Approved :: MIT License
Classifier: Operating System :: OS Independent
Classifier: Programming Language :: Python :: 3
Classifier: Programming Language :: Python :: 3.10
Classifier: Programming Language :: Python :: 3.11
Classifier: Programming Language :: Python :: 3.12
Classifier: Topic :: Scientific/Engineering :: Information Analysis
Classifier: Topic :: Text Processing :: Linguistic
Requires-Python: >=3.10
License-File: LICENSE
Requires-Dist: numpy>=1.24.0
Requires-Dist: pandas>=2.0.0
Requires-Dist: scikit-learn>=1.3.0
Requires-Dist: scipy>=1.11.0
Requires-Dist: matplotlib>=3.7.0
Requires-Dist: tqdm>=4.65.0
Requires-Dist: pypdf>=3.0.0
Provides-Extra: ai
Requires-Dist: requests>=2.28.0; extra == "ai"
Provides-Extra: stylometrix
Requires-Dist: stylo_metrix>=0.1.9; extra == "stylometrix"
Requires-Dist: spacy>=3.7.0; extra == "stylometrix"
Requires-Dist: regex>=2023.0.0; extra == "stylometrix"
Provides-Extra: all
Requires-Dist: stylometry-cli[ai,stylometrix]; extra == "all"
Provides-Extra: dev
Requires-Dist: pytest>=7.0.0; extra == "dev"
Requires-Dist: pytest-cov>=4.0.0; extra == "dev"
Requires-Dist: black>=23.0.0; extra == "dev"
Requires-Dist: isort>=5.12.0; extra == "dev"
Requires-Dist: mypy>=1.0.0; extra == "dev"
Requires-Dist: build>=1.0.0; extra == "dev"
Requires-Dist: twine>=4.0.0; extra == "dev"
Dynamic: license-file
